ateeth_todo_cli/__init__.py
ateeth_todo_cli/ateeth_todo_cli/data/tasks.json
ateeth_todo_cli/cli.py
ateeth_todo_cli/model/Task.py
ateeth_todo_cli-0.1.3.dist-info/entry_points.txt
ateeth_todo_cli-0.1.3.dist-info/METADATA
ateeth_todo_cli-0.1.3.dist-info/WHEEL
ateeth_todo_cli-0.1.3.dist-info/RECORD
